<!-- @(#) $Id: decoder.xml,v 1.166 2010/06/15 12:52:01 dcid Exp $
  -  OSSEC log decoder.
  -  Author: Daniel B. Cid
  -  License: http://www.ossec.net/en/licensing.html
  -->

<!-- IIS6 WWW W3C log format.
  - #Fields: date time s-sitename s-computername s-ip cs-method cs-uri-stem
  cs-uri-query s-port cs-username c-ip cs-version cs(User-Agent)
  cs(Cookie) cs(Referer) cs-host sc-status sc-substatus sc-win32-status
  sc-bytes cs-bytes time-taken
  - Examples:
  - 2007-01-22 05:00:11 W3SVC1 HOSTNAME 1.1.1.1 POST /SimpleAuthWebService/SimpleAuth.asmx - 80 - 2.2.2.2 HTTP/1.1 Windows-Update-Agent - - hostname 200 0 0 1467 841 3
1
  -->
<decoder name="web-accesslog-iis6">
  <parent>windows-date-format</parent>
  <type>web-log</type>
  <use_own_name>true</use_own_name>
  <prematch offset="after_parent">^W3SVC\d+ \S+ \S+ \S+ </prematch>
  <regex offset="after_prematch">^(\S+ \S+) \d+ \S+ (\d+.\d+.\d+.\d+) </regex>
  <regex>\S+ \S+ \S+ \S+ \S+ (\d+) </regex>
  <order>url, srcip, id</order>
</decoder>


